README.rst
setup.py
mlperceptron/__init__.py
mlperceptron/mlperceptron.py
mlperceptron.egg-info/PKG-INFO
mlperceptron.egg-info/SOURCES.txt
mlperceptron.egg-info/dependency_links.txt
mlperceptron.egg-info/not-zip-safe
mlperceptron.egg-info/requires.txt
mlperceptron.egg-info/top_level.txt
tests/__init__.py
tests/test_mlperceptron.py