Metadata-Version: 1.1
Name: mlperceptron
Version: 0.2
Summary: Python implementation of multilayer perceptron neural network from scratch.
Home-page: https://github.com/paulokuong/mlperceptron
Author: Paulo Kuong
Author-email: paulo.kuong@gmail.com
License: MIT
Keywords: Neural Network NN neural network multilayer perceptron machine learning logistic classifier
Platform: UNKNOWN
Classifier: Development Status :: 3 - Alpha
Classifier: License :: OSI Approved :: MIT License
Classifier: Programming Language :: Python :: 3.4
